LICENSE
MANIFEST.in
README.md
RELEASE-VERSION
setup.py
version.py
dossier/__init__.py
dossier.store.egg-info/PKG-INFO
dossier.store.egg-info/SOURCES.txt
dossier.store.egg-info/dependency_links.txt
dossier.store.egg-info/entry_points.txt
dossier.store.egg-info/namespace_packages.txt
dossier.store.egg-info/not-zip-safe
dossier.store.egg-info/requires.txt
dossier.store.egg-info/top_level.txt
dossier/store/__init__.py
dossier/store/elastic.py
dossier/store/run.py
dossier/store/store.py
dossier/store/tests/__init__.py
dossier/store/tests/test_elastic.py
dossier/store/tests/test_store.py