Metadata-Version: 1.1
Name: dossier.store
Version: 0.5.1.dev3
Summary: Feature collection storage for DossierStack
Home-page: http://github.com/dossier/dossier.store
Author: Diffeo, Inc.
Author-email: support@diffeo.com
License: 
